[
  {
    "id": 1,
    "name": "Masala Chai",
    "description": "Spiced Indian tea with milk",
    "longDescription": "Traditional Indian tea brewed with black tea leaves, milk, and a blend of warming spices like cardamom, cinnamon, and ginger.",
    "price": "4€",
    "image": "/nila-5th-image.png",
    "images": ["/nila-5th-image.png", "/nila-6th-image.png", "/nila-1st-image.png"],
    "likes": 33,
    "isVegetarian": true,
    "badge": "Classic",
    "badgeColor": "gold",
    "tags": ["coffee", "leaf", "flame"],
    "category": ["hot", "tea", "spiced"],
    "mainCategory": "hot"
  },
  {
    "id": 2,
    "name": "Filter Coffee",
    "description": "South Indian strong coffee",
    "longDescription": "Rich and aromatic coffee brewed using a traditional South Indian filter, served with milk and sugar.",
    "price": "4€",
    "image": "/nila-6th-image.png",
    "images": ["/nila-6th-image.png", "/nila-1st-image.png", "/nila-2nd-image.png"],
    "likes": 21,
    "isVegetarian": true,
    "badge": "Popular",
    "badgeColor": "green",
    "tags": ["coffee", "coffee", "star"],
    "category": ["hot", "coffee", "south-indian"],
    "mainCategory": "coffee"
  },
  {
    "id": 3,
    "name": "Mango Lassi",
    "description": "Sweet mango yogurt drink",
    "longDescription": "Refreshing and creamy yogurt-based drink blended with ripe mangoes and a touch of cardamom.",
    "price": "5€",
    "image": "/nila-1st-image.png",
    "images": ["/nila-1st-image.png", "/nila-2nd-image.png", "/nila-3rd-image.png"],
    "likes": 27,
    "isVegetarian": true,
    "badge": "Summer Special",
    "badgeColor": "gold",
    "tags": ["milk", "bottle-wine", "sun"],
    "category": ["cold", "lassi", "sweet"],
    "mainCategory": "cold"
  },
  {
    "id": 4,
    "name": "Rose Sherbet",
    "description": "Chilled rose-flavored drink",
    "longDescription": "A cooling beverage made with rose syrup, lemon juice, and chilled water, perfect for summer.",
    "price": "4€",
    "image": "/nila-2nd-image.png",
    "images": ["/nila-2nd-image.png", "/nila-3rd-image.png", "/nila-4th-image.png"],
    "likes": 18,
    "isVegetarian": true,
    "badge": "Refreshing",
    "badgeColor": "purple",
    "tags": ["flower", "droplet", "citrus"],
    "category": ["cold", "sweet", "non-alcoholic"],
    "mainCategory": "cold"
  },
  {
    "id": 5,
    "name": "Kingfisher Beer",
    "description": "Popular Indian lager",
    "longDescription": "Crisp and refreshing lager beer, a favorite across India.",
    "price": "6€",
    "image": "/nila-3rd-image.png",
    "images": ["/nila-3rd-image.png", "/nila-4th-image.png", "/nila-5th-image.png"],
    "likes": 22,
    "isVegetarian": true,
    "badge": "Alcoholic",
    "badgeColor": "green",
    "tags": ["beer", "bottle-wine", "star"],
    "category": ["alcoholic", "cold", "beer"],
    "mainCategory": "alcoholic"
  },
  {
    "id": 6,
    "name": "Old Monk Rum",
    "description": "Iconic Indian dark rum",
    "longDescription": "Smooth and full-bodied dark rum, enjoyed neat or in cocktails.",
    "price": "7€",
    "image": "/nila-4th-image.png",
    "images": ["/nila-4th-image.png", "/nila-5th-image.png", "/nila-6th-image.png"],
    "likes": 15,
    "isVegetarian": true,
    "badge": "Alcoholic",
    "badgeColor": "purple",
    "tags": ["wine", "anchor", "star"],
    "category": ["alcoholic", "rum", "cocktail"],
    "mainCategory": "alcoholic"
  },
  {
    "id": 7,
    "name": "Jaljeera",
    "description": "Spiced lemonade with cumin",
    "longDescription": "Tangy and spicy drink made with lemon juice, cumin, mint, and black salt, served chilled.",
    "price": "4€",
    "image": "/nila-5th-image.png",
    "images": ["/nila-5th-image.png", "/nila-6th-image.png", "/nila-1st-image.png"],
    "likes": 19,
    "isVegetarian": true,
    "badge": "Digestive",
    "badgeColor": "green",
    "tags": ["citrus", "droplet", "bottle-wine"],
    "category": ["cold", "spiced", "non-alcoholic"],
    "mainCategory": "cold"
  },
  {
    "id": 8,
    "name": "Sula Red Wine",
    "description": "Indian red wine",
    "longDescription": "Smooth and fruity red wine from the vineyards of Nashik.",
    "price": "8€",
    "image": "/nila-6th-image.png",
    "images": ["/nila-6th-image.png", "/nila-1st-image.png", "/nila-2nd-image.png"],
    "likes": 13,
    "isVegetarian": true,
    "badge": "Alcoholic",
    "badgeColor": "gold",
    "tags": ["wine", "wine", "star"],
    "category": ["alcoholic", "wine", "red"],
    "mainCategory": "alcoholic"
  },
  {
    "id": 9,
    "name": "Thandai",
    "description": "Festive milk drink with nuts and spices",
    "longDescription": "Traditional Holi drink made with milk, almonds, fennel, rose, and cardamom, served chilled.",
    "price": "5€",
    "image": "/nila-1st-image.png",
    "images": ["/nila-1st-image.png", "/nila-2nd-image.png", "/nila-3rd-image.png"],
    "likes": 16,
    "isVegetarian": true,
    "badge": "Festive",
    "badgeColor": "gold",
    "tags": ["milk", "nut", "bottle-wine"],
    "category": ["cold", "milk", "sweet"],
    "mainCategory": "cold"
  },
  {
    "id": 10,
    "name": "Hot Turmeric Latte",
    "description": "Golden milk with turmeric and spices",
    "longDescription": "Warm and comforting drink made with milk, turmeric, ginger, and cinnamon.",
    "price": "5€",
    "image": "/nila-2nd-image.png",
    "images": ["/nila-2nd-image.png", "/nila-3rd-image.png", "/nila-4th-image.png"],
    "likes": 20,
    "isVegetarian": true,
    "badge": "Healthy",
    "badgeColor": "green",
    "tags": ["milk", "flame", "leaf"],
    "category": ["hot", "milk", "healthy"],
    "mainCategory": "hot"
  }
]